OBRequests/__init__.py
OBRequests/_awaiting.py
OBRequests/_blocking.py
OBRequests/_call_back.py
OBRequests/_catch_all.py
OBRequests/_conditional.py
OBRequests/_defaults.py
OBRequests/_defined.py
OBRequests/_errors.py
OBRequests/_methods.py
OBRequests/_route.py
OBRequests/_types.py
OBRequests/tests/__init__.py
OBRequests/tests/awaiting.py
OBRequests/tests/base.py
OBRequests/tests/blocking.py
OBRequests-2.0.1.dist-info/LICENSE
OBRequests-2.0.1.dist-info/METADATA
OBRequests-2.0.1.dist-info/WHEEL
OBRequests-2.0.1.dist-info/top_level.txt
OBRequests-2.0.1.dist-info/RECORD
