Metadata-Version: 2.1
Name: OBRequests
Version: 2.0.1
Summary: Modern typed requests for Python 3 built on-top of HTTPX
Home-page: https://obrequests.readthedocs.io/en/latest/
Author: WardPearce
Author-email: wardpearce@pm.me
License: GNU General Public License v3.0
Platform: UNKNOWN
Requires-Python: >=3.6
License-File: LICENSE
Requires-Dist: httpx (>=0.19.0)
Requires-Dist: asynctest
Requires-Dist: sphinx-material
Requires-Dist: sphinxcontrib-trio
